git_portfolio/__init__.py
git_portfolio/__main__.py
git_portfolio/config_manager.py
git_portfolio/domain/__init__.py
git_portfolio/domain/config.py
git_portfolio/domain/gh_connection_settings.py
git_portfolio/domain/issue.py
git_portfolio/domain/pull_request.py
git_portfolio/domain/pull_request_merge.py
git_portfolio/github_service.py
git_portfolio/prompt.py
git_portfolio/prompt_validation.py
git_portfolio/py.typed
git_portfolio/request_objects/__init__.py
git_portfolio/request_objects/issue_list.py
git_portfolio/responses.py
git_portfolio/use_cases/__init__.py
git_portfolio/use_cases/command_checker.py
git_portfolio/use_cases/config_init.py
git_portfolio/use_cases/config_repos.py
git_portfolio/use_cases/gh.py
git_portfolio/use_cases/gh_close_issue.py
git_portfolio/use_cases/gh_create_issue.py
git_portfolio/use_cases/gh_create_pr.py
git_portfolio/use_cases/gh_delete_branch.py
git_portfolio/use_cases/gh_merge_pr.py
git_portfolio/use_cases/gh_reopen_issue.py
git_portfolio/use_cases/git.py
git_portfolio/use_cases/git_clone.py
git_portfolio/use_cases/poetry.py
git_portfolio/views.py
git_portfolio-1.1.1.dist-info/entry_points.txt
git_portfolio-1.1.1.dist-info/LICENSE
git_portfolio-1.1.1.dist-info/WHEEL
git_portfolio-1.1.1.dist-info/METADATA
git_portfolio-1.1.1.dist-info/RECORD
