Metadata-Version: 2.1
Name: git-portfolio
Version: 1.1.1
Summary: Git Portfolio
Home-page: https://github.com/staticdev/git-portfolio
License: MIT
Author: staticdev
Author-email: staticdev-support@proton.me
Requires-Python: >=3.9.0
Classifier: License :: OSI Approved :: MIT License
Classifier: Programming Language :: Python :: 3
Classifier: Programming Language :: Python :: 3.9
Classifier: Programming Language :: Python :: 3.10
Classifier: Programming Language :: Python :: 3.11
Classifier: Programming Language :: Python :: 3.10
Classifier: Programming Language :: Python :: 3.11
Classifier: Programming Language :: Python :: 3.9
Requires-Dist: click (>=8.0.0,<9)
Requires-Dist: github3.py (>=3.2.0)
Requires-Dist: inquirer (>=2.10.1)
Requires-Dist: pyyaml (>=5.3.1)
Project-URL: Changelog, https://github.com/staticdev/git-portfolio/releases
Project-URL: Documentation, https://git-portfolio.readthedocs.io
Project-URL: Repository, https://github.com/staticdev/git-portfolio
